citycatio/__init__.py
citycatio/model.py
citycatio/output.py
citycatio/utils.py
citycatio/inputs/__init__.py
citycatio/inputs/boundaries.py
citycatio/inputs/buildings.py
citycatio/inputs/configuration.py
citycatio/inputs/dem.py
citycatio/inputs/flow.py
citycatio/inputs/flow_polygons.py
citycatio/inputs/friction.py
citycatio/inputs/green_areas.py
citycatio/inputs/rainfall.py
citycatio/inputs/rainfall_polygons.py
citycatio-0.9.0.dist-info/LICENSE
citycatio-0.9.0.dist-info/METADATA
citycatio-0.9.0.dist-info/WHEEL
citycatio-0.9.0.dist-info/entry_points.txt
citycatio-0.9.0.dist-info/top_level.txt
citycatio-0.9.0.dist-info/RECORD
