Metadata-Version: 2.1
Name: citycatio
Version: 0.9.0
Summary: CityCAT extension to create inputs and convert outputs
Home-page: https://github.com/nclwater/citycatio
Author: Fergus McClean
Author-email: fergus.mcclean@ncl.ac.uk
License: GPL-3.0
Platform: UNKNOWN
License-File: LICENSE
Requires-Dist: gdal
Requires-Dist: geopandas
Requires-Dist: rasterio
Requires-Dist: netCDF4
Requires-Dist: pandas
Requires-Dist: numpy
